setup.py
open_data/__init__.py
open_data/open_data.py
open_data.egg-info/PKG-INFO
open_data.egg-info/SOURCES.txt
open_data.egg-info/dependency_links.txt
open_data.egg-info/top_level.txt
open_data/api/__init__.py
open_data/api/api.py
open_data/api/test_api.py
open_data/api/xml2dict/__init__.py
open_data/api/xml2dict/object_dict.py
open_data/api/xml2dict/xml2dict.py