Metadata-Version: 1.0
Name: open-data
Version: 1.0
Summary: Python wrapper for the Microsoft Open Data APIs.
Home-page: https://github.com/codeforamerica/microsoft_open_data_python
Author: Zach Williams
Author-email: zach@codeforamerica.org
License: BSD
Keywords: open data,microsoft open data,microsoft
Platform: UNKNOWN
Classifier: Development Status :: 5 - Production/Stable
Classifier: Intended Audience :: Developers
Classifier: Natural Language :: English
Classifier: Operating System :: OS Independent
Classifier: Programming Language :: Python :: 2
Classifier: Topic :: Internet
Classifier: Topic :: Internet :: WWW/HTTP
